friendly_styles/__init__.py
friendly_styles/friendly_dark.py
friendly_styles/friendly_light.py
friendly_styles-0.2.dist-info/LICENSE
friendly_styles-0.2.dist-info/METADATA
friendly_styles-0.2.dist-info/WHEEL
friendly_styles-0.2.dist-info/entry_points.txt
friendly_styles-0.2.dist-info/top_level.txt
friendly_styles-0.2.dist-info/RECORD
