Metadata-Version: 2.1
Name: friendly_styles
Version: 0.2
Summary: Pygments styles designed for friendly/friendly-traceback
Home-page: https://github.com/friendly-traceback/friendly_styles
Author: André Roberge
Author-email: andre.roberge@gmail.com
License: MIT
Classifier: Development Status :: 4 - Beta
Classifier: Environment :: Plugins
Classifier: Intended Audience :: Developers
Classifier: License :: OSI Approved :: MIT License
Classifier: Operating System :: OS Independent
Classifier: Programming Language :: Python
Classifier: Programming Language :: Python :: 3
Classifier: Topic :: Software Development :: Libraries :: Python Modules
License-File: LICENSE
